enti/__init__.py
enti/__main__.py
enti/debugging.py
enti/run.py
enti/settings.py
enti/version.py
enti/api/__init__.py
enti/api/entity.py
enti/api/processor.py
enti/api/regex.py
enti/api/tokens.py
enti/ext/__init__.py
enti/processors/__init__.py
enti/processors/clean.py
enti/processors/extract.py
enti/processors/nltk.py
enti/steps/__init__.py
enti/steps/regex/__init__.py
enti/steps/regex/quantify.py
enti/steps/regex/sub.py
enti/steps/utility/__init__.py
enti/steps/utility/list_extract.py
enti/steps/utility/text_to_data.py
enti-0.0.1.dist-info/LICENSE
enti-0.0.1.dist-info/METADATA
enti-0.0.1.dist-info/WHEEL
enti-0.0.1.dist-info/top_level.txt
enti-0.0.1.dist-info/RECORD
