Metadata-Version: 2.1
Name: enti
Version: 0.0.1
Summary: A toolkit for unstructured text
Home-page: https://github.com/istresearch/enti
Author: Joe Goulet
Author-email: joseph.goulet@istresearch.com
License: UNKNOWN
Platform: UNKNOWN
Classifier: Programming Language :: Python :: 3.6
Classifier: License :: OSI Approved :: MIT License
Classifier: Operating System :: OS Independent
Requires-Dist: nltk
Requires-Dist: numpy
